flactomp3/__init__.py
flactomp3/main.py
flactomp3/version_getter.py
flactomp3-1.0.1.dist-info/METADATA
flactomp3-1.0.1.dist-info/WHEEL
flactomp3-1.0.1.dist-info/entry_points.txt
flactomp3-1.0.1.dist-info/licenses/LICENSE
flactomp3-1.0.1.dist-info/RECORD
