Metadata-Version: 2.1
Name: flactomp3
Version: 1.0.1
Summary: Convert FLAC audio files into MP3 files.
Project-URL: Homepage, https://github.com/haru52/flactomp3#readme
Project-URL: Bug Tracker, https://github.com/haru52/flactomp3/issues
Project-URL: Repository, https://github.com/haru52/flactomp3.git
Author: haru
License-Expression: MIT
License-File: LICENSE
Keywords: audio,converter,encoder,flac,mp3
Classifier: License :: OSI Approved :: MIT License
Classifier: Operating System :: OS Independent
Classifier: Programming Language :: Python :: 3
Requires-Python: ~=3.11
Requires-Dist: click~=8.1
